brewinglib/cli/__init__.py
brewinglib/cli/cli.py
brewinglib/cli/py.typed
brewinglib/cli/testing.py
brewinglib_cli-0.0.6.dist-info/METADATA
brewinglib_cli-0.0.6.dist-info/WHEEL
brewinglib_cli-0.0.6.dist-info/RECORD
