Metadata-Version: 2.4
Name: brewinglib-cli
Version: 0.0.6
Summary: brewinglib's CLI system, a wrapper around Tiangolo's typer.
Project-URL: Homepage, https://mikemcowie.github.io/brewing/
Project-URL: Documentation, https://mikemcowie.github.io/brewing/
Project-URL: Repository, https://github.com/mikemcowie/brewing
Project-URL: Issues, https://github.com/mikemcowie/brewing
Project-URL: Releases, https://github.com/mikemcowie/brewing/releases
Author-email: Mike Cowie <24739590+mikemcowie@users.noreply.github.com>
Requires-Python: >=3.13
Requires-Dist: pydantic>=2.11.7
Requires-Dist: typer>=0.16.1
